toggl2jira/__init__.py
toggl2jira/cli.py
toggl2jira/config.py
toggl2jira/jira.py
toggl2jira/toggl.py
toggl2jira-2.0.0.dist-info/METADATA
toggl2jira-2.0.0.dist-info/WHEEL
toggl2jira-2.0.0.dist-info/entry_points.txt
toggl2jira-2.0.0.dist-info/RECORD
