Metadata-Version: 2.4
Name: toggl2jira
Version: 2.0.0
Summary: Replicate toggl time entries to Jira worklogs
Author: Jakob Schlagenhaufer
Requires-Python: >=3.13
Classifier: Programming Language :: Python :: 3
Classifier: Programming Language :: Python :: 3.13
Classifier: Programming Language :: Python :: 3.14
Requires-Dist: python-dateutil (>=2.9.0.post0,<3.0.0)
Requires-Dist: python-dotenv (>=1.0.1,<2.0.0)
Requires-Dist: requests (>=2.32.3,<3.0.0)
Requires-Dist: truststore (>=0.10.1,<0.11.0)
